<?xml version="1.0" encoding="utf-8"?>
<EntityRelationships xmlns:xsi="http://www.w3.org/2001/XMLSchema-instance">
  <EntityRelationship Name="account_bookableresource_AccountId">
    <EntityRelationshipType>OneToMany</EntityRelationshipType>
    <IntroducedVersion>8.1.0.0</IntroducedVersion>
    <IsHierarchical>0</IsHierarchical>
    <ReferencingEntityName>BookableResource</ReferencingEntityName>
    <ReferencedEntityName>Account</ReferencedEntityName>
    <CascadeAssign>NoCascade</CascadeAssign>
    <CascadeDelete>RemoveLink</CascadeDelete>
    <CascadeReparent>NoCascade</CascadeReparent>
    <CascadeShare>NoCascade</CascadeShare>
    <CascadeUnshare>NoCascade</CascadeUnshare>
    <CascadeRollupView>NoCascade</CascadeRollupView>
    <ReferencingAttributeName>AccountId</ReferencingAttributeName>
    <RelationshipDescription>
      <Descriptions>
        <Description description="account_bookableresource_AccountId" languagecode="1033" />
      </Descriptions>
    </RelationshipDescription>
    <EntityRelationshipRoles>
      <EntityRelationshipRole>
        <NavPaneDisplayOption>UseCollectionName</NavPaneDisplayOption>
        <NavPaneArea>Details</NavPaneArea>
        <NavPaneOrder>10000</NavPaneOrder>
        <NavigationPropertyName>AccountId</NavigationPropertyName>
        <RelationshipRoleType>1</RelationshipRoleType>
      </EntityRelationshipRole>
      <EntityRelationshipRole>
        <RelationshipRoleType>0</RelationshipRoleType>
      </EntityRelationshipRole>
    </EntityRelationshipRoles>
  </EntityRelationship>
  <EntityRelationship Name="Account_Emails">
    <EntityRelationshipType>OneToMany</EntityRelationshipType>
    <IntroducedVersion>5.0.0.0</IntroducedVersion>
    <IsHierarchical>0</IsHierarchical>
    <ReferencingEntityName>Email</ReferencingEntityName>
    <ReferencedEntityName>Account</ReferencedEntityName>
    <CascadeAssign>Cascade</CascadeAssign>
    <CascadeDelete>Cascade</CascadeDelete>
    <CascadeReparent>Cascade</CascadeReparent>
    <CascadeShare>Cascade</CascadeShare>
    <CascadeUnshare>Cascade</CascadeUnshare>
    <CascadeRollupView>NoCascade</CascadeRollupView>
    <ReferencingAttributeName>RegardingObjectId</ReferencingAttributeName>
    <RelationshipDescription>
      <Descriptions>
        <Description description="Unique identifier of the object with which the e-mail is associated." languagecode="1033" />
      </Descriptions>
    </RelationshipDescription>
  </EntityRelationship>
  <EntityRelationship Name="account_entitlement_Account">
    <EntityRelationshipType>OneToMany</EntityRelationshipType>
    <IntroducedVersion>6.1.0.0</IntroducedVersion>
    <IsHierarchical>0</IsHierarchical>
    <ReferencingEntityName>Entitlement</ReferencingEntityName>
    <ReferencedEntityName>Account</ReferencedEntityName>
    <CascadeAssign>NoCascade</CascadeAssign>
    <CascadeDelete>RemoveLink</CascadeDelete>
    <CascadeReparent>NoCascade</CascadeReparent>
    <CascadeShare>NoCascade</CascadeShare>
    <CascadeUnshare>NoCascade</CascadeUnshare>
    <ReferencingAttributeName>AccountId</ReferencingAttributeName>
    <RelationshipDescription>
      <Descriptions>
        <Description description="account_entitlement_Account" languagecode="1033" />
      </Descriptions>
    </RelationshipDescription>
    <EntityRelationshipRoles>
      <EntityRelationshipRole>
        <NavPaneDisplayOption>UseCollectionName</NavPaneDisplayOption>
        <NavPaneArea>Details</NavPaneArea>
        <NavPaneOrder>10000</NavPaneOrder>
        <NavigationPropertyName>accountid</NavigationPropertyName>
        <RelationshipRoleType>1</RelationshipRoleType>
      </EntityRelationshipRole>
      <EntityRelationshipRole>
        <RelationshipRoleType>0</RelationshipRoleType>
      </EntityRelationshipRole>
    </EntityRelationshipRoles>
  </EntityRelationship>
  <EntityRelationship Name="account_entitlement_Customer">
    <EntityRelationshipType>OneToMany</EntityRelationshipType>
    <IntroducedVersion>6.1.0.0</IntroducedVersion>
    <IsHierarchical>0</IsHierarchical>
    <ReferencingEntityName>Entitlement</ReferencingEntityName>
    <ReferencedEntityName>Account</ReferencedEntityName>
    <CascadeAssign>NoCascade</CascadeAssign>
    <CascadeDelete>Restrict</CascadeDelete>
    <CascadeReparent>NoCascade</CascadeReparent>
    <CascadeShare>NoCascade</CascadeShare>
    <CascadeUnshare>NoCascade</CascadeUnshare>
    <ReferencingAttributeName>CustomerId</ReferencingAttributeName>
    <RelationshipDescription>
      <Descriptions>
        <Description description="contact_entitlement_Customer" languagecode="1033" />
      </Descriptions>
    </RelationshipDescription>
    <EntityRelationshipRoles>
      <EntityRelationshipRole>
        <NavPaneDisplayOption>UseCollectionName</NavPaneDisplayOption>
        <NavPaneArea>Details</NavPaneArea>
        <NavPaneOrder>10000</NavPaneOrder>
        <NavigationPropertyName>customerid_account</NavigationPropertyName>
        <RelationshipRoleType>1</RelationshipRoleType>
      </EntityRelationshipRole>
      <EntityRelationshipRole>
        <RelationshipRoleType>0</RelationshipRoleType>
      </EntityRelationshipRole>
    </EntityRelationshipRoles>
  </EntityRelationship>
  <EntityRelationship Name="account_master_account">
    <EntityRelationshipType>OneToMany</EntityRelationshipType>
    <IntroducedVersion>5.0.0.0</IntroducedVersion>
    <IsHierarchical>0</IsHierarchical>
    <ReferencingEntityName>Account</ReferencingEntityName>
    <ReferencedEntityName>Account</ReferencedEntityName>
    <CascadeAssign>NoCascade</CascadeAssign>
    <CascadeDelete>RemoveLink</CascadeDelete>
    <CascadeReparent>NoCascade</CascadeReparent>
    <CascadeShare>NoCascade</CascadeShare>
    <CascadeUnshare>NoCascade</CascadeUnshare>
    <CascadeRollupView>NoCascade</CascadeRollupView>
    <ReferencingAttributeName>MasterId</ReferencingAttributeName>
    <RelationshipDescription>
      <Descriptions>
        <Description description="Shows the master account that the account was merged with." languagecode="1033" />
      </Descriptions>
    </RelationshipDescription>
  </EntityRelationship>
  <EntityRelationship Name="Account_New_AccountProducts">
    <EntityRelationshipType>OneToMany</EntityRelationshipType>
    <IsCustomizable>1</IsCustomizable>
    <IntroducedVersion>1.0</IntroducedVersion>
    <IsHierarchical>0</IsHierarchical>
    <ReferencingEntityName>New_AccountProduct</ReferencingEntityName>
    <ReferencedEntityName>Account</ReferencedEntityName>
    <CascadeAssign>Cascade</CascadeAssign>
    <CascadeDelete>Cascade</CascadeDelete>
    <CascadeReparent>Cascade</CascadeReparent>
    <CascadeShare>Cascade</CascadeShare>
    <CascadeUnshare>Cascade</CascadeUnshare>
    <CascadeRollupView>NoCascade</CascadeRollupView>
    <IsValidForAdvancedFind>1</IsValidForAdvancedFind>
    <ReferencingAttributeName>New_AccountId</ReferencingAttributeName>
    <RelationshipDescription>
      <Descriptions>
        <Description description="Unique identifier of the account with which the account product is associated." languagecode="1033" />
      </Descriptions>
    </RelationshipDescription>
    <EntityRelationshipRoles>
      <EntityRelationshipRole>
        <NavPaneDisplayOption>UseLabel</NavPaneDisplayOption>
        <NavPaneArea>Sales</NavPaneArea>
        <NavPaneOrder>10000</NavPaneOrder>
        <NavigationPropertyName>new_accountid</NavigationPropertyName>
        <CustomLabels>
          <CustomLabel description="Account Products" languagecode="1033" />
        </CustomLabels>
        <RelationshipRoleType>1</RelationshipRoleType>
      </EntityRelationshipRole>
      <EntityRelationshipRole>
        <NavigationPropertyName>Account_New_AccountProducts</NavigationPropertyName>
        <RelationshipRoleType>0</RelationshipRoleType>
      </EntityRelationshipRole>
    </EntityRelationshipRoles>
  </EntityRelationship>
  <EntityRelationship Name="account_parent_account">
    <EntityRelationshipType>OneToMany</EntityRelationshipType>
    <IntroducedVersion>5.0.0.0</IntroducedVersion>
    <IsHierarchical>1</IsHierarchical>
    <ReferencingEntityName>Account</ReferencingEntityName>
    <ReferencedEntityName>Account</ReferencedEntityName>
    <CascadeAssign>Cascade</CascadeAssign>
    <CascadeDelete>RemoveLink</CascadeDelete>
    <CascadeReparent>Cascade</CascadeReparent>
    <CascadeShare>Cascade</CascadeShare>
    <CascadeUnshare>Cascade</CascadeUnshare>
    <CascadeRollupView>NoCascade</CascadeRollupView>
    <ReferencingAttributeName>ParentAccountId</ReferencingAttributeName>
    <RelationshipDescription>
      <Descriptions>
        <Description description="Choose the parent account associated with this account to show parent and child businesses in reporting and analytics." languagecode="1033" />
      </Descriptions>
    </RelationshipDescription>
    <EntityRelationshipRoles>
      <EntityRelationshipRole>
        <NavPaneDisplayOption>UseCollectionName</NavPaneDisplayOption>
        <NavPaneArea>Details</NavPaneArea>
        <NavPaneOrder>40</NavPaneOrder>
        <NavigationPropertyName>parentaccountid</NavigationPropertyName>
        <RelationshipRoleType>1</RelationshipRoleType>
      </EntityRelationshipRole>
      <EntityRelationshipRole>
        <RelationshipRoleType>0</RelationshipRoleType>
      </EntityRelationshipRole>
    </EntityRelationshipRoles>
  </EntityRelationship>
  <EntityRelationship Name="Account_ServiceAppointments">
    <EntityRelationshipType>OneToMany</EntityRelationshipType>
    <IntroducedVersion>5.0.0.0</IntroducedVersion>
    <IsHierarchical>0</IsHierarchical>
    <ReferencingEntityName>ServiceAppointment</ReferencingEntityName>
    <ReferencedEntityName>Account</ReferencedEntityName>
    <CascadeAssign>Cascade</CascadeAssign>
    <CascadeDelete>RemoveLink</CascadeDelete>
    <CascadeReparent>Cascade</CascadeReparent>
    <CascadeShare>Cascade</CascadeShare>
    <CascadeUnshare>Cascade</CascadeUnshare>
    <ReferencingAttributeName>RegardingObjectId</ReferencingAttributeName>
    <RelationshipDescription>
      <Descriptions>
        <Description description="Unique identifier of the object with which the service activity is associated." languagecode="1033" />
      </Descriptions>
    </RelationshipDescription>
  </EntityRelationship>
  <EntityRelationship Name="account_tra_timeexpenses">
    <EntityRelationshipType>OneToMany</EntityRelationshipType>
    <IsCustomizable>1</IsCustomizable>
    <IntroducedVersion>1.0</IntroducedVersion>
    <IsHierarchical>0</IsHierarchical>
    <ReferencingEntityName>tra_timeexpense</ReferencingEntityName>
    <ReferencedEntityName>Account</ReferencedEntityName>
    <CascadeAssign>Cascade</CascadeAssign>
    <CascadeDelete>Cascade</CascadeDelete>
    <CascadeReparent>Cascade</CascadeReparent>
    <CascadeShare>Cascade</CascadeShare>
    <CascadeUnshare>Cascade</CascadeUnshare>
    <ReferencingAttributeName>RegardingObjectId</ReferencingAttributeName>
    <RelationshipDescription>
      <Descriptions>
        <Description description="Unique identifier of the object with which the activity is associated." languagecode="1033" />
      </Descriptions>
    </RelationshipDescription>
  </EntityRelationship>
  <EntityRelationship Name="adx_accountproduct">
    <EntityRelationshipType>ManyToMany</EntityRelationshipType>
    <IntroducedVersion>1.0.0.6</IntroducedVersion>
    <IsHierarchical>0</IsHierarchical>
    <FirstEntityName>Account</FirstEntityName>
    <SecondEntityName>Product</SecondEntityName>
    <IntersectEntityName>adx_accountproduct</IntersectEntityName>
    <IsValidForAdvancedFind>1</IsValidForAdvancedFind>
    <EntityRelationshipRoles>
      <EntityRelationshipRole>
        <NavPaneDisplayOption>DoNotDisplay</NavPaneDisplayOption>
        <NavigationPropertyName>adx_accountproduct</NavigationPropertyName>
        <CustomLabels>
          <CustomLabel description="" languagecode="1033" />
        </CustomLabels>
        <AssociationRoleOrdinal>1</AssociationRoleOrdinal>
      </EntityRelationshipRole>
      <EntityRelationshipRole>
        <NavPaneDisplayOption>DoNotDisplay</NavPaneDisplayOption>
        <NavigationPropertyName>adx_accountproduct</NavigationPropertyName>
        <CustomLabels>
          <CustomLabel description="" languagecode="1033" />
        </CustomLabels>
        <AssociationRoleOrdinal>2</AssociationRoleOrdinal>
      </EntityRelationshipRole>
    </EntityRelationshipRoles>
  </EntityRelationship>
  <EntityRelationship Name="contact_customer_accounts">
    <EntityRelationshipType>OneToMany</EntityRelationshipType>
    <IntroducedVersion>5.0.0.0</IntroducedVersion>
    <IsHierarchical>0</IsHierarchical>
    <ReferencingEntityName>Contact</ReferencingEntityName>
    <ReferencedEntityName>Account</ReferencedEntityName>
    <CascadeAssign>Cascade</CascadeAssign>
    <CascadeDelete>Cascade</CascadeDelete>
    <CascadeReparent>Cascade</CascadeReparent>
    <CascadeShare>Cascade</CascadeShare>
    <CascadeUnshare>Cascade</CascadeUnshare>
    <CascadeRollupView>NoCascade</CascadeRollupView>
    <ReferencingAttributeName>ParentCustomerId</ReferencingAttributeName>
    <RelationshipDescription>
      <Descriptions>
        <Description description="Select the parent account or parent contact for the contact to provide a quick link to additional details, such as financial information, activities, and opportunities." languagecode="1033" />
      </Descriptions>
    </RelationshipDescription>
    <EntityRelationshipRoles>
      <EntityRelationshipRole>
        <NavPaneDisplayOption>UseCollectionName</NavPaneDisplayOption>
        <NavPaneArea>Details</NavPaneArea>
        <NavPaneOrder>50</NavPaneOrder>
        <NavigationPropertyName>parentcustomerid_account</NavigationPropertyName>
        <RelationshipRoleType>1</RelationshipRoleType>
      </EntityRelationshipRole>
      <EntityRelationshipRole>
        <RelationshipRoleType>0</RelationshipRoleType>
      </EntityRelationshipRole>
    </EntityRelationshipRoles>
  </EntityRelationship>
  <EntityRelationship Name="contract_billingcustomer_accounts">
    <EntityRelationshipType>OneToMany</EntityRelationshipType>
    <IntroducedVersion>5.0.0.0</IntroducedVersion>
    <IsHierarchical>0</IsHierarchical>
    <ReferencingEntityName>Contract</ReferencingEntityName>
    <ReferencedEntityName>Account</ReferencedEntityName>
    <CascadeAssign>NoCascade</CascadeAssign>
    <CascadeDelete>Restrict</CascadeDelete>
    <CascadeReparent>NoCascade</CascadeReparent>
    <CascadeShare>NoCascade</CascadeShare>
    <CascadeUnshare>NoCascade</CascadeUnshare>
    <ReferencingAttributeName>BillingCustomerId</ReferencingAttributeName>
    <RelationshipDescription>
      <Descriptions>
        <Description description="contract_billingcustomer_contacts" languagecode="1033" />
      </Descriptions>
    </RelationshipDescription>
  </EntityRelationship>
  <EntityRelationship Name="contract_customer_accounts">
    <EntityRelationshipType>OneToMany</EntityRelationshipType>
    <IntroducedVersion>5.0.0.0</IntroducedVersion>
    <IsHierarchical>0</IsHierarchical>
    <ReferencingEntityName>Contract</ReferencingEntityName>
    <ReferencedEntityName>Account</ReferencedEntityName>
    <CascadeAssign>Cascade</CascadeAssign>
    <CascadeDelete>Cascade</CascadeDelete>
    <CascadeReparent>Cascade</CascadeReparent>
    <CascadeShare>Cascade</CascadeShare>
    <CascadeUnshare>Cascade</CascadeUnshare>
    <ReferencingAttributeName>CustomerId</ReferencingAttributeName>
    <RelationshipDescription>
      <Descriptions>
        <Description description="contract_customer_contacts" languagecode="1033" />
      </Descriptions>
    </RelationshipDescription>
    <EntityRelationshipRoles>
      <EntityRelationshipRole>
        <NavPaneDisplayOption>UseCollectionName</NavPaneDisplayOption>
        <NavPaneArea>Service</NavPaneArea>
        <NavPaneOrder>20</NavPaneOrder>
        <NavigationPropertyName>customerid_account</NavigationPropertyName>
        <RelationshipRoleType>1</RelationshipRoleType>
      </EntityRelationshipRole>
      <EntityRelationshipRole>
        <RelationshipRoleType>0</RelationshipRoleType>
      </EntityRelationshipRole>
    </EntityRelationshipRoles>
  </EntityRelationship>
  <EntityRelationship Name="contractlineitem_customer_accounts">
    <EntityRelationshipType>OneToMany</EntityRelationshipType>
    <IntroducedVersion>5.0.0.0</IntroducedVersion>
    <IsHierarchical>0</IsHierarchical>
    <ReferencingEntityName>ContractDetail</ReferencingEntityName>
    <ReferencedEntityName>Account</ReferencedEntityName>
    <CascadeAssign>NoCascade</CascadeAssign>
    <CascadeDelete>Cascade</CascadeDelete>
    <CascadeReparent>NoCascade</CascadeReparent>
    <CascadeShare>NoCascade</CascadeShare>
    <CascadeUnshare>NoCascade</CascadeUnshare>
    <ReferencingAttributeName>CustomerId</ReferencingAttributeName>
    <RelationshipDescription>
      <Descriptions>
        <Description description="contractlineitem_customer_contacts" languagecode="1033" />
      </Descriptions>
    </RelationshipDescription>
  </EntityRelationship>
  <EntityRelationship Name="incident_customer_accounts">
    <EntityRelationshipType>OneToMany</EntityRelationshipType>
    <IntroducedVersion>5.0.0.0</IntroducedVersion>
    <IsHierarchical>0</IsHierarchical>
    <ReferencingEntityName>Incident</ReferencingEntityName>
    <ReferencedEntityName>Account</ReferencedEntityName>
    <CascadeAssign>NoCascade</CascadeAssign>
    <CascadeDelete>Cascade</CascadeDelete>
    <CascadeReparent>Cascade</CascadeReparent>
    <CascadeShare>Cascade</CascadeShare>
    <CascadeUnshare>Cascade</CascadeUnshare>
    <ReferencingAttributeName>CustomerId</ReferencingAttributeName>
    <RelationshipDescription>
      <Descriptions>
        <Description description="Select the customer account or contact to provide a quick link to additional customer details, such as account information, activities, and opportunities." languagecode="1033" />
      </Descriptions>
    </RelationshipDescription>
    <EntityRelationshipRoles>
      <EntityRelationshipRole>
        <NavPaneDisplayOption>UseCollectionName</NavPaneDisplayOption>
        <NavPaneArea>Service</NavPaneArea>
        <NavPaneOrder>10</NavPaneOrder>
        <NavigationPropertyName>customerid_account</NavigationPropertyName>
        <RelationshipRoleType>1</RelationshipRoleType>
      </EntityRelationshipRole>
      <EntityRelationshipRole>
        <RelationshipRoleType>0</RelationshipRoleType>
      </EntityRelationshipRole>
    </EntityRelationshipRoles>
  </EntityRelationship>
  <EntityRelationship Name="invoice_customer_accounts">
    <EntityRelationshipType>OneToMany</EntityRelationshipType>
    <IntroducedVersion>5.0.0.0</IntroducedVersion>
    <IsHierarchical>0</IsHierarchical>
    <ReferencingEntityName>Invoice</ReferencingEntityName>
    <ReferencedEntityName>Account</ReferencedEntityName>
    <CascadeAssign>Cascade</CascadeAssign>
    <CascadeDelete>Restrict</CascadeDelete>
    <CascadeReparent>Cascade</CascadeReparent>
    <CascadeShare>Cascade</CascadeShare>
    <CascadeUnshare>Cascade</CascadeUnshare>
    <ReferencingAttributeName>CustomerId</ReferencingAttributeName>
    <RelationshipDescription>
      <Descriptions>
        <Description description="invoice_customer_contacts" languagecode="1033" />
      </Descriptions>
    </RelationshipDescription>
    <EntityRelationshipRoles>
      <EntityRelationshipRole>
        <NavPaneDisplayOption>UseCollectionName</NavPaneDisplayOption>
        <NavPaneArea>Sales</NavPaneArea>
        <NavPaneOrder>40</NavPaneOrder>
        <NavigationPropertyName>customerid_account</NavigationPropertyName>
        <RelationshipRoleType>1</RelationshipRoleType>
      </EntityRelationshipRole>
      <EntityRelationshipRole>
        <RelationshipRoleType>0</RelationshipRoleType>
      </EntityRelationshipRole>
    </EntityRelationshipRoles>
  </EntityRelationship>
  <EntityRelationship Name="lead_customer_accounts">
    <EntityRelationshipType>OneToMany</EntityRelationshipType>
    <IntroducedVersion>5.0.0.0</IntroducedVersion>
    <IsHierarchical>0</IsHierarchical>
    <ReferencingEntityName>Lead</ReferencingEntityName>
    <ReferencedEntityName>Account</ReferencedEntityName>
    <CascadeAssign>Cascade</CascadeAssign>
    <CascadeDelete>Cascade</CascadeDelete>
    <CascadeReparent>Cascade</CascadeReparent>
    <CascadeShare>Cascade</CascadeShare>
    <CascadeUnshare>Cascade</CascadeUnshare>
    <ReferencingAttributeName>CustomerId</ReferencingAttributeName>
    <RelationshipDescription>
      <Descriptions>
        <Description description="lead_customer_contacts" languagecode="1033" />
      </Descriptions>
    </RelationshipDescription>
  </EntityRelationship>
  <EntityRelationship Name="lead_parent_account">
    <EntityRelationshipType>OneToMany</EntityRelationshipType>
    <IntroducedVersion>5.0.0.0</IntroducedVersion>
    <IsHierarchical>0</IsHierarchical>
    <ReferencingEntityName>Lead</ReferencingEntityName>
    <ReferencedEntityName>Account</ReferencedEntityName>
    <CascadeAssign>NoCascade</CascadeAssign>
    <CascadeDelete>RemoveLink</CascadeDelete>
    <CascadeReparent>NoCascade</CascadeReparent>
    <CascadeShare>NoCascade</CascadeShare>
    <CascadeUnshare>NoCascade</CascadeUnshare>
    <ReferencingAttributeName>ParentAccountId</ReferencingAttributeName>
    <RelationshipDescription>
      <Descriptions>
        <Description description="lead_parent_account" languagecode="1033" />
      </Descriptions>
    </RelationshipDescription>
    <EntityRelationshipRoles>
      <EntityRelationshipRole>
        <NavPaneDisplayOption>UseCollectionName</NavPaneDisplayOption>
        <NavPaneArea>Sales</NavPaneArea>
        <NavPaneOrder>0</NavPaneOrder>
        <NavigationPropertyName>parentaccountid</NavigationPropertyName>
        <RelationshipRoleType>1</RelationshipRoleType>
      </EntityRelationshipRole>
      <EntityRelationshipRole>
        <RelationshipRoleType>0</RelationshipRoleType>
      </EntityRelationshipRole>
    </EntityRelationshipRoles>
  </EntityRelationship>
  <EntityRelationship Name="msa_account_incident">
    <EntityRelationshipType>OneToMany</EntityRelationshipType>
    <IntroducedVersion>1.0.21</IntroducedVersion>
    <IsHierarchical>0</IsHierarchical>
    <ReferencingEntityName>Incident</ReferencingEntityName>
    <ReferencedEntityName>Account</ReferencedEntityName>
    <CascadeAssign>NoCascade</CascadeAssign>
    <CascadeDelete>Restrict</CascadeDelete>
    <CascadeReparent>NoCascade</CascadeReparent>
    <CascadeShare>NoCascade</CascadeShare>
    <CascadeUnshare>NoCascade</CascadeUnshare>
    <CascadeRollupView>NoCascade</CascadeRollupView>
    <IsValidForAdvancedFind>1</IsValidForAdvancedFind>
    <ReferencingAttributeName>msa_partnerid</ReferencingAttributeName>
    <RelationshipDescription>
      <Descriptions>
        <Description description="Creates a Relationship between a Partner (account) and a case for indirect service arrangements." languagecode="1033" />
      </Descriptions>
    </RelationshipDescription>
    <EntityRelationshipRoles>
      <EntityRelationshipRole>
        <NavPaneDisplayOption>UseLabel</NavPaneDisplayOption>
        <NavPaneArea>Service</NavPaneArea>
        <NavPaneOrder>100100</NavPaneOrder>
        <NavigationPropertyName>msa_partnerid</NavigationPropertyName>
        <CustomLabels>
          <CustomLabel description="Partner Cases" languagecode="1033" />
        </CustomLabels>
        <RelationshipRoleType>1</RelationshipRoleType>
      </EntityRelationshipRole>
      <EntityRelationshipRole>
        <RelationshipRoleType>0</RelationshipRoleType>
      </EntityRelationshipRole>
    </EntityRelationshipRoles>
  </EntityRelationship>
  <EntityRelationship Name="msa_account_managingpartner">
    <EntityRelationshipType>OneToMany</EntityRelationshipType>
    <IntroducedVersion>1.0.21</IntroducedVersion>
    <IsHierarchical>0</IsHierarchical>
    <ReferencingEntityName>Account</ReferencingEntityName>
    <ReferencedEntityName>Account</ReferencedEntityName>
    <CascadeAssign>NoCascade</CascadeAssign>
    <CascadeDelete>RemoveLink</CascadeDelete>
    <CascadeReparent>NoCascade</CascadeReparent>
    <CascadeShare>NoCascade</CascadeShare>
    <CascadeUnshare>NoCascade</CascadeUnshare>
    <CascadeRollupView>NoCascade</CascadeRollupView>
    <IsValidForAdvancedFind>1</IsValidForAdvancedFind>
    <ReferencingAttributeName>msa_managingpartnerid</ReferencingAttributeName>
    <RelationshipDescription>
      <Descriptions>
        <Description description="Unique identifier for Account associated with Account." languagecode="1033" />
      </Descriptions>
    </RelationshipDescription>
    <EntityRelationshipRoles>
      <EntityRelationshipRole>
        <NavPaneDisplayOption>UseLabel</NavPaneDisplayOption>
        <NavPaneArea>Details</NavPaneArea>
        <NavPaneOrder>100400</NavPaneOrder>
        <NavigationPropertyName>msa_managingpartnerid</NavigationPropertyName>
        <CustomLabels>
          <CustomLabel description="Managed Accounts" languagecode="1033" />
        </CustomLabels>
        <RelationshipRoleType>1</RelationshipRoleType>
      </EntityRelationshipRole>
      <EntityRelationshipRole>
        <RelationshipRoleType>0</RelationshipRoleType>
      </EntityRelationshipRole>
    </EntityRelationshipRoles>
  </EntityRelationship>
  <EntityRelationship Name="msa_contact_managingpartner">
    <EntityRelationshipType>OneToMany</EntityRelationshipType>
    <IntroducedVersion>1.0.21</IntroducedVersion>
    <IsHierarchical>0</IsHierarchical>
    <ReferencingEntityName>Contact</ReferencingEntityName>
    <ReferencedEntityName>Account</ReferencedEntityName>
    <CascadeAssign>NoCascade</CascadeAssign>
    <CascadeDelete>RemoveLink</CascadeDelete>
    <CascadeReparent>NoCascade</CascadeReparent>
    <CascadeShare>NoCascade</CascadeShare>
    <CascadeUnshare>NoCascade</CascadeUnshare>
    <CascadeRollupView>NoCascade</CascadeRollupView>
    <IsValidForAdvancedFind>1</IsValidForAdvancedFind>
    <ReferencingAttributeName>msa_managingpartnerid</ReferencingAttributeName>
    <RelationshipDescription>
      <Descriptions>
        <Description description="Unique identifier for Account associated with Contact." languagecode="1033" />
      </Descriptions>
    </RelationshipDescription>
    <EntityRelationshipRoles>
      <EntityRelationshipRole>
        <NavPaneDisplayOption>UseLabel</NavPaneDisplayOption>
        <NavPaneArea>Details</NavPaneArea>
        <NavPaneOrder>100500</NavPaneOrder>
        <NavigationPropertyName>msa_managingpartnerid</NavigationPropertyName>
        <CustomLabels>
          <CustomLabel description="Managed Contacts" languagecode="1033" />
        </CustomLabels>
        <RelationshipRoleType>1</RelationshipRoleType>
      </EntityRelationshipRole>
      <EntityRelationshipRole>
        <RelationshipRoleType>0</RelationshipRoleType>
      </EntityRelationshipRole>
    </EntityRelationshipRoles>
  </EntityRelationship>
  <EntityRelationship Name="msa_partner_opportunity">
    <EntityRelationshipType>OneToMany</EntityRelationshipType>
    <IntroducedVersion>1.0.21</IntroducedVersion>
    <IsHierarchical>0</IsHierarchical>
    <ReferencingEntityName>Opportunity</ReferencingEntityName>
    <ReferencedEntityName>Account</ReferencedEntityName>
    <CascadeAssign>NoCascade</CascadeAssign>
    <CascadeDelete>Restrict</CascadeDelete>
    <CascadeReparent>NoCascade</CascadeReparent>
    <CascadeShare>NoCascade</CascadeShare>
    <CascadeUnshare>NoCascade</CascadeUnshare>
    <CascadeRollupView>NoCascade</CascadeRollupView>
    <IsValidForAdvancedFind>1</IsValidForAdvancedFind>
    <ReferencingAttributeName>msa_partnerid</ReferencingAttributeName>
    <RelationshipDescription>
      <Descriptions>
        <Description description="Unique identifier for Account associated with Opportunity." languagecode="1033" />
      </Descriptions>
    </RelationshipDescription>
    <EntityRelationshipRoles>
      <EntityRelationshipRole>
        <NavPaneDisplayOption>UseLabel</NavPaneDisplayOption>
        <NavPaneArea>Sales</NavPaneArea>
        <NavPaneOrder>100100</NavPaneOrder>
        <NavigationPropertyName>msa_partnerid</NavigationPropertyName>
        <CustomLabels>
          <CustomLabel description="Partner Opportunities" languagecode="1033" />
        </CustomLabels>
        <RelationshipRoleType>1</RelationshipRoleType>
      </EntityRelationshipRole>
      <EntityRelationshipRole>
        <RelationshipRoleType>0</RelationshipRoleType>
      </EntityRelationshipRole>
    </EntityRelationshipRoles>
  </EntityRelationship>
  <EntityRelationship Name="msdyn_account_msdyn_responseoutcome_Account">
    <EntityRelationshipType>OneToMany</EntityRelationshipType>
    <IntroducedVersion>2.0.2.47</IntroducedVersion>
    <IsHierarchical>0</IsHierarchical>
    <ReferencingEntityName>msdyn_responseoutcome</ReferencingEntityName>
    <ReferencedEntityName>Account</ReferencedEntityName>
    <CascadeAssign>NoCascade</CascadeAssign>
    <CascadeDelete>RemoveLink</CascadeDelete>
    <CascadeReparent>NoCascade</CascadeReparent>
    <CascadeShare>NoCascade</CascadeShare>
    <CascadeUnshare>NoCascade</CascadeUnshare>
    <CascadeRollupView>NoCascade</CascadeRollupView>
    <IsValidForAdvancedFind>1</IsValidForAdvancedFind>
    <ReferencingAttributeName>msdyn_Account</ReferencingAttributeName>
    <RelationshipDescription>
      <Descriptions>
        <Description description="Shows the account associated with the action." languagecode="1033" />
      </Descriptions>
    </RelationshipDescription>
    <EntityRelationshipRoles>
      <EntityRelationshipRole>
        <NavPaneDisplayOption>UseCollectionName</NavPaneDisplayOption>
        <NavPaneArea>Details</NavPaneArea>
        <NavPaneOrder>10000</NavPaneOrder>
        <NavigationPropertyName>msdyn_Account</NavigationPropertyName>
        <CustomLabels>
          <CustomLabel description="" languagecode="1033" />
        </CustomLabels>
        <RelationshipRoleType>1</RelationshipRoleType>
      </EntityRelationshipRole>
      <EntityRelationshipRole>
        <RelationshipRoleType>0</RelationshipRoleType>
      </EntityRelationshipRole>
    </EntityRelationshipRoles>
  </EntityRelationship>
  <EntityRelationship Name="msdyn_account_msdyn_surveyinvite_AccountId">
    <EntityRelationshipType>OneToMany</EntityRelationshipType>
    <IntroducedVersion>2.0.2.47</IntroducedVersion>
    <IsHierarchical>0</IsHierarchical>
    <ReferencingEntityName>msdyn_surveyinvite</ReferencingEntityName>
    <ReferencedEntityName>Account</ReferencedEntityName>
    <CascadeAssign>NoCascade</CascadeAssign>
    <CascadeDelete>RemoveLink</CascadeDelete>
    <CascadeReparent>NoCascade</CascadeReparent>
    <CascadeShare>NoCascade</CascadeShare>
    <CascadeUnshare>NoCascade</CascadeUnshare>
    <CascadeRollupView>NoCascade</CascadeRollupView>
    <IsValidForAdvancedFind>1</IsValidForAdvancedFind>
    <ReferencingAttributeName>msdyn_AccountId</ReferencingAttributeName>
    <RelationshipDescription>
      <Descriptions>
        <Description description="Shows the account associated with the survey activity." languagecode="1033" />
      </Descriptions>
    </RelationshipDescription>
    <EntityRelationshipRoles>
      <EntityRelationshipRole>
        <NavPaneDisplayOption>UseCollectionName</NavPaneDisplayOption>
        <NavPaneArea>Details</NavPaneArea>
        <NavPaneOrder>10000</NavPaneOrder>
        <NavigationPropertyName>msdyn_AccountId</NavigationPropertyName>
        <CustomLabels>
          <CustomLabel description="" languagecode="1033" />
        </CustomLabels>
        <RelationshipRoleType>1</RelationshipRoleType>
      </EntityRelationshipRole>
      <EntityRelationshipRole>
        <RelationshipRoleType>0</RelationshipRoleType>
      </EntityRelationshipRole>
    </EntityRelationshipRoles>
  </EntityRelationship>
  <EntityRelationship Name="msdyn_account_msdyn_surveyresponse_Account">
    <EntityRelationshipType>OneToMany</EntityRelationshipType>
    <IntroducedVersion>2.0.2.47</IntroducedVersion>
    <IsHierarchical>0</IsHierarchical>
    <ReferencingEntityName>msdyn_surveyresponse</ReferencingEntityName>
    <ReferencedEntityName>Account</ReferencedEntityName>
    <CascadeAssign>NoCascade</CascadeAssign>
    <CascadeDelete>RemoveLink</CascadeDelete>
    <CascadeReparent>NoCascade</CascadeReparent>
    <CascadeShare>NoCascade</CascadeShare>
    <CascadeUnshare>NoCascade</CascadeUnshare>
    <CascadeRollupView>NoCascade</CascadeRollupView>
    <IsValidForAdvancedFind>1</IsValidForAdvancedFind>
    <ReferencingAttributeName>msdyn_Account</ReferencingAttributeName>
    <RelationshipDescription>
      <Descriptions>
        <Description description="Shows the account associated with the survey response." languagecode="1033" />
      </Descriptions>
    </RelationshipDescription>
    <EntityRelationshipRoles>
      <EntityRelationshipRole>
        <NavPaneDisplayOption>UseCollectionName</NavPaneDisplayOption>
        <NavPaneArea>Details</NavPaneArea>
        <NavPaneOrder>10000</NavPaneOrder>
        <NavigationPropertyName>msdyn_Account</NavigationPropertyName>
        <CustomLabels>
          <CustomLabel description="" languagecode="1033" />
        </CustomLabels>
        <RelationshipRoleType>1</RelationshipRoleType>
      </EntityRelationshipRole>
      <EntityRelationshipRole>
        <RelationshipRoleType>0</RelationshipRoleType>
      </EntityRelationshipRole>
    </EntityRelationshipRoles>
  </EntityRelationship>
  <EntityRelationship Name="new_account_account_agent1">
    <EntityRelationshipType>OneToMany</EntityRelationshipType>
    <IsCustomizable>1</IsCustomizable>
    <IntroducedVersion>1.0</IntroducedVersion>
    <IsHierarchical>0</IsHierarchical>
    <ReferencingEntityName>Account</ReferencingEntityName>
    <ReferencedEntityName>Account</ReferencedEntityName>
    <CascadeAssign>NoCascade</CascadeAssign>
    <CascadeDelete>RemoveLink</CascadeDelete>
    <CascadeReparent>NoCascade</CascadeReparent>
    <CascadeShare>NoCascade</CascadeShare>
    <CascadeUnshare>NoCascade</CascadeUnshare>
    <CascadeRollupView>NoCascade</CascadeRollupView>
    <IsValidForAdvancedFind>1</IsValidForAdvancedFind>
    <ReferencingAttributeName>New_DataAgentId</ReferencingAttributeName>
    <RelationshipDescription>
      <Descriptions>
        <Description description="Agent relationship for Chart/Data&#xA;Created by Christopher request 22/01/2014" languagecode="1033" />
      </Descriptions>
    </RelationshipDescription>
    <EntityRelationshipRoles>
      <EntityRelationshipRole>
        <NavPaneDisplayOption>DoNotDisplay</NavPaneDisplayOption>
        <NavPaneArea>Details</NavPaneArea>
        <NavPaneOrder>10000</NavPaneOrder>
        <NavigationPropertyName>new_dataagentid_account</NavigationPropertyName>
        <CustomLabels>
          <CustomLabel description="" languagecode="1033" />
        </CustomLabels>
        <RelationshipRoleType>1</RelationshipRoleType>
      </EntityRelationshipRole>
      <EntityRelationshipRole>
        <NavigationPropertyName>new_account_account_agent1</NavigationPropertyName>
        <RelationshipRoleType>0</RelationshipRoleType>
      </EntityRelationshipRole>
    </EntityRelationshipRoles>
  </EntityRelationship>
  <EntityRelationship Name="new_account_account_agent2">
    <EntityRelationshipType>OneToMany</EntityRelationshipType>
    <IsCustomizable>1</IsCustomizable>
    <IntroducedVersion>1.0</IntroducedVersion>
    <IsHierarchical>0</IsHierarchical>
    <ReferencingEntityName>Account</ReferencingEntityName>
    <ReferencedEntityName>Account</ReferencedEntityName>
    <CascadeAssign>NoCascade</CascadeAssign>
    <CascadeDelete>RemoveLink</CascadeDelete>
    <CascadeReparent>NoCascade</CascadeReparent>
    <CascadeShare>NoCascade</CascadeShare>
    <CascadeUnshare>NoCascade</CascadeUnshare>
    <CascadeRollupView>NoCascade</CascadeRollupView>
    <IsValidForAdvancedFind>1</IsValidForAdvancedFind>
    <ReferencingAttributeName>New_HardwareDealerId</ReferencingAttributeName>
    <RelationshipDescription>
      <Descriptions>
        <Description description="Created by Christopher request 22.01.2015" languagecode="1033" />
      </Descriptions>
    </RelationshipDescription>
    <EntityRelationshipRoles>
      <EntityRelationshipRole>
        <NavPaneDisplayOption>DoNotDisplay</NavPaneDisplayOption>
        <NavPaneArea>Details</NavPaneArea>
        <NavPaneOrder>10000</NavPaneOrder>
        <NavigationPropertyName>new_hardwaredealerid_account</NavigationPropertyName>
        <CustomLabels>
          <CustomLabel description="" languagecode="1033" />
        </CustomLabels>
        <RelationshipRoleType>1</RelationshipRoleType>
      </EntityRelationshipRole>
      <EntityRelationshipRole>
        <NavigationPropertyName>new_account_account_agent2</NavigationPropertyName>
        <RelationshipRoleType>0</RelationshipRoleType>
      </EntityRelationshipRole>
    </EntityRelationshipRoles>
  </EntityRelationship>
  <EntityRelationship Name="new_account_account_agent3">
    <EntityRelationshipType>OneToMany</EntityRelationshipType>
    <IsCustomizable>1</IsCustomizable>
    <IntroducedVersion>1.0</IntroducedVersion>
    <IsHierarchical>0</IsHierarchical>
    <ReferencingEntityName>Account</ReferencingEntityName>
    <ReferencedEntityName>Account</ReferencedEntityName>
    <CascadeAssign>NoCascade</CascadeAssign>
    <CascadeDelete>RemoveLink</CascadeDelete>
    <CascadeReparent>NoCascade</CascadeReparent>
    <CascadeShare>NoCascade</CascadeShare>
    <CascadeUnshare>NoCascade</CascadeUnshare>
    <CascadeRollupView>NoCascade</CascadeRollupView>
    <IsValidForAdvancedFind>1</IsValidForAdvancedFind>
    <ReferencingAttributeName>New_ServicePartnerId</ReferencingAttributeName>
    <RelationshipDescription>
      <Descriptions>
        <Description description="Created By Christopher request on 22/01/2015" languagecode="1033" />
      </Descriptions>
    </RelationshipDescription>
    <EntityRelationshipRoles>
      <EntityRelationshipRole>
        <NavPaneDisplayOption>DoNotDisplay</NavPaneDisplayOption>
        <NavPaneArea>Details</NavPaneArea>
        <NavPaneOrder>10000</NavPaneOrder>
        <NavigationPropertyName>new_servicepartnerid_account</NavigationPropertyName>
        <CustomLabels>
          <CustomLabel description="" languagecode="1033" />
        </CustomLabels>
        <RelationshipRoleType>1</RelationshipRoleType>
      </EntityRelationshipRole>
      <EntityRelationshipRole>
        <NavigationPropertyName>new_account_account_agent3</NavigationPropertyName>
        <RelationshipRoleType>0</RelationshipRoleType>
      </EntityRelationshipRole>
    </EntityRelationshipRoles>
  </EntityRelationship>
  <EntityRelationship Name="new_account_incident">
    <EntityRelationshipType>OneToMany</EntityRelationshipType>
    <IsCustomizable>1</IsCustomizable>
    <IntroducedVersion>1.0</IntroducedVersion>
    <IsHierarchical>0</IsHierarchical>
    <ReferencingEntityName>Incident</ReferencingEntityName>
    <ReferencedEntityName>Account</ReferencedEntityName>
    <CascadeAssign>NoCascade</CascadeAssign>
    <CascadeDelete>Restrict</CascadeDelete>
    <CascadeReparent>NoCascade</CascadeReparent>
    <CascadeShare>NoCascade</CascadeShare>
    <CascadeUnshare>NoCascade</CascadeUnshare>
    <CascadeRollupView>NoCascade</CascadeRollupView>
    <IsValidForAdvancedFind>1</IsValidForAdvancedFind>
    <ReferencingAttributeName>New_VesselId</ReferencingAttributeName>
    <RelationshipDescription>
      <Descriptions>
        <Description description="Unique identifier for Account associated with Case." languagecode="1033" />
      </Descriptions>
    </RelationshipDescription>
    <EntityRelationshipRoles>
      <EntityRelationshipRole>
        <NavPaneDisplayOption>DoNotDisplay</NavPaneDisplayOption>
        <NavPaneArea>Service</NavPaneArea>
        <NavPaneOrder>10000</NavPaneOrder>
        <NavigationPropertyName>new_vesselid</NavigationPropertyName>
        <CustomLabels>
          <CustomLabel description="Vessel Cases" languagecode="1033" />
        </CustomLabels>
        <RelationshipRoleType>1</RelationshipRoleType>
      </EntityRelationshipRole>
      <EntityRelationshipRole>
        <NavigationPropertyName>new_account_incident</NavigationPropertyName>
        <RelationshipRoleType>0</RelationshipRoleType>
      </EntityRelationshipRole>
    </EntityRelationshipRoles>
  </EntityRelationship>
  <EntityRelationship Name="new_account_new_accountproduct">
    <EntityRelationshipType>ManyToMany</EntityRelationshipType>
    <IsCustomizable>1</IsCustomizable>
    <IntroducedVersion>1.17.3.30</IntroducedVersion>
    <IsHierarchical>0</IsHierarchical>
    <FirstEntityName>Account</FirstEntityName>
    <SecondEntityName>New_AccountProduct</SecondEntityName>
    <IntersectEntityName>new_account_new_accountproduct</IntersectEntityName>
    <IsValidForAdvancedFind>1</IsValidForAdvancedFind>
    <EntityRelationshipRoles>
      <EntityRelationshipRole>
        <NavPaneDisplayOption>DoNotDisplay</NavPaneDisplayOption>
        <NavigationPropertyName>new_account_new_accountproduct</NavigationPropertyName>
        <CustomLabels>
          <CustomLabel description="" languagecode="1033" />
        </CustomLabels>
        <AssociationRoleOrdinal>1</AssociationRoleOrdinal>
      </EntityRelationshipRole>
      <EntityRelationshipRole>
        <NavPaneDisplayOption>DoNotDisplay</NavPaneDisplayOption>
        <NavigationPropertyName>new_account_new_accountproduct</NavigationPropertyName>
        <CustomLabels>
          <CustomLabel description="" languagecode="1033" />
        </CustomLabels>
        <AssociationRoleOrdinal>2</AssociationRoleOrdinal>
      </EntityRelationshipRole>
    </EntityRelationshipRoles>
  </EntityRelationship>
  <EntityRelationship Name="new_account_new_agreement">
    <EntityRelationshipType>OneToMany</EntityRelationshipType>
    <IsCustomizable>1</IsCustomizable>
    <IntroducedVersion>1.0</IntroducedVersion>
    <IsHierarchical>0</IsHierarchical>
    <ReferencingEntityName>New_agreement</ReferencingEntityName>
    <ReferencedEntityName>Account</ReferencedEntityName>
    <CascadeAssign>NoCascade</CascadeAssign>
    <CascadeDelete>RemoveLink</CascadeDelete>
    <CascadeReparent>NoCascade</CascadeReparent>
    <CascadeShare>NoCascade</CascadeShare>
    <CascadeUnshare>NoCascade</CascadeUnshare>
    <CascadeRollupView>NoCascade</CascadeRollupView>
    <IsValidForAdvancedFind>1</IsValidForAdvancedFind>
    <ReferencingAttributeName>New_customer_id</ReferencingAttributeName>
    <RelationshipDescription>
      <Descriptions>
        <Description description="Unique identifier for Account associated with Agreement." languagecode="1033" />
      </Descriptions>
    </RelationshipDescription>
    <EntityRelationshipRoles>
      <EntityRelationshipRole>
        <NavPaneDisplayOption>UseCollectionName</NavPaneDisplayOption>
        <NavPaneArea>Details</NavPaneArea>
        <NavPaneOrder>10000</NavPaneOrder>
        <NavigationPropertyName>new_customer_id</NavigationPropertyName>
        <CustomLabels>
          <CustomLabel description="" languagecode="1033" />
        </CustomLabels>
        <RelationshipRoleType>1</RelationshipRoleType>
      </EntityRelationshipRole>
      <EntityRelationshipRole>
        <NavigationPropertyName>new_account_new_agreement</NavigationPropertyName>
        <RelationshipRoleType>0</RelationshipRoleType>
      </EntityRelationshipRole>
    </EntityRelationshipRoles>
  </EntityRelationship>
  <EntityRelationship Name="new_account_new_certificate_of_aps">
    <EntityRelationshipType>OneToMany</EntityRelationshipType>
    <IsCustomizable>1</IsCustomizable>
    <IntroducedVersion>1.0</IntroducedVersion>
    <IsHierarchical>0</IsHierarchical>
    <ReferencingEntityName>New_certificate_of_aps</ReferencingEntityName>
    <ReferencedEntityName>Account</ReferencedEntityName>
    <CascadeAssign>NoCascade</CascadeAssign>
    <CascadeDelete>RemoveLink</CascadeDelete>
    <CascadeReparent>NoCascade</CascadeReparent>
    <CascadeShare>NoCascade</CascadeShare>
    <CascadeUnshare>NoCascade</CascadeUnshare>
    <CascadeRollupView>NoCascade</CascadeRollupView>
    <IsValidForAdvancedFind>1</IsValidForAdvancedFind>
    <ReferencingAttributeName>New_VesselId</ReferencingAttributeName>
    <RelationshipDescription>
      <Descriptions>
        <Description description="" languagecode="1033" />
      </Descriptions>
    </RelationshipDescription>
    <EntityRelationshipRoles>
      <EntityRelationshipRole>
        <NavPaneDisplayOption>UseCollectionName</NavPaneDisplayOption>
        <NavPaneArea>Details</NavPaneArea>
        <NavPaneOrder>10000</NavPaneOrder>
        <NavigationPropertyName>new_vesselid</NavigationPropertyName>
        <CustomLabels>
          <CustomLabel description="" languagecode="1033" />
        </CustomLabels>
        <RelationshipRoleType>1</RelationshipRoleType>
      </EntityRelationshipRole>
      <EntityRelationshipRole>
        <NavigationPropertyName>new_account_new_certificate_of_aps</NavigationPropertyName>
        <RelationshipRoleType>0</RelationshipRoleType>
      </EntityRelationshipRole>
    </EntityRelationshipRoles>
  </EntityRelationship>
  <EntityRelationship Name="new_account_new_certificate_of_aps1">
    <EntityRelationshipType>OneToMany</EntityRelationshipType>
    <IsCustomizable>1</IsCustomizable>
    <IntroducedVersion>1.0</IntroducedVersion>
    <IsHierarchical>0</IsHierarchical>
    <ReferencingEntityName>New_certificate_of_aps</ReferencingEntityName>
    <ReferencedEntityName>Account</ReferencedEntityName>
    <CascadeAssign>NoCascade</CascadeAssign>
    <CascadeDelete>RemoveLink</CascadeDelete>
    <CascadeReparent>NoCascade</CascadeReparent>
    <CascadeShare>NoCascade</CascadeShare>
    <CascadeUnshare>NoCascade</CascadeUnshare>
    <CascadeRollupView>NoCascade</CascadeRollupView>
    <IsValidForAdvancedFind>1</IsValidForAdvancedFind>
    <ReferencingAttributeName>New_ServiceAgentId</ReferencingAttributeName>
    <RelationshipDescription>
      <Descriptions>
        <Description description="Service Agent (Account)" languagecode="1033" />
      </Descriptions>
    </RelationshipDescription>
    <EntityRelationshipRoles>
      <EntityRelationshipRole>
        <NavPaneDisplayOption>DoNotDisplay</NavPaneDisplayOption>
        <NavigationPropertyName>new_serviceagentid</NavigationPropertyName>
        <CustomLabels>
          <CustomLabel description="" languagecode="1033" />
        </CustomLabels>
        <RelationshipRoleType>1</RelationshipRoleType>
      </EntityRelationshipRole>
      <EntityRelationshipRole>
        <NavigationPropertyName>new_account_new_certificate_of_aps1</NavigationPropertyName>
        <RelationshipRoleType>0</RelationshipRoleType>
      </EntityRelationshipRole>
    </EntityRelationshipRoles>
  </EntityRelationship>
  <EntityRelationship Name="new_account_new_certificateofcompliance">
    <EntityRelationshipType>OneToMany</EntityRelationshipType>
    <IsCustomizable>1</IsCustomizable>
    <IntroducedVersion>1.0</IntroducedVersion>
    <IsHierarchical>0</IsHierarchical>
    <ReferencingEntityName>New_certificateofcompliance</ReferencingEntityName>
    <ReferencedEntityName>Account</ReferencedEntityName>
    <CascadeAssign>NoCascade</CascadeAssign>
    <CascadeDelete>RemoveLink</CascadeDelete>
    <CascadeReparent>NoCascade</CascadeReparent>
    <CascadeShare>NoCascade</CascadeShare>
    <CascadeUnshare>NoCascade</CascadeUnshare>
    <CascadeRollupView>NoCascade</CascadeRollupView>
    <IsValidForAdvancedFind>1</IsValidForAdvancedFind>
    <ReferencingAttributeName>New_VesselId</ReferencingAttributeName>
    <RelationshipDescription>
      <Descriptions>
        <Description description="Link to Account (Previously used for Vessels)" languagecode="1033" />
      </Descriptions>
    </RelationshipDescription>
    <EntityRelationshipRoles>
      <EntityRelationshipRole>
        <NavPaneDisplayOption>UseCollectionName</NavPaneDisplayOption>
        <NavPaneArea>Service</NavPaneArea>
        <NavPaneOrder>10000</NavPaneOrder>
        <NavigationPropertyName>new_vesselid</NavigationPropertyName>
        <CustomLabels>
          <CustomLabel description="" languagecode="1033" />
        </CustomLabels>
        <RelationshipRoleType>1</RelationshipRoleType>
      </EntityRelationshipRole>
      <EntityRelationshipRole>
        <NavigationPropertyName>new_account_new_certificateofcompliance</NavigationPropertyName>
        <RelationshipRoleType>0</RelationshipRoleType>
      </EntityRelationshipRole>
    </EntityRelationshipRoles>
  </EntityRelationship>
  <EntityRelationship Name="new_account_new_certificateofcompliance1">
    <EntityRelationshipType>OneToMany</EntityRelationshipType>
    <IsCustomizable>1</IsCustomizable>
    <IntroducedVersion>1.0</IntroducedVersion>
    <IsHierarchical>0</IsHierarchical>
    <ReferencingEntityName>New_certificateofcompliance</ReferencingEntityName>
    <ReferencedEntityName>Account</ReferencedEntityName>
    <CascadeAssign>NoCascade</CascadeAssign>
    <CascadeDelete>RemoveLink</CascadeDelete>
    <CascadeReparent>NoCascade</CascadeReparent>
    <CascadeShare>NoCascade</CascadeShare>
    <CascadeUnshare>NoCascade</CascadeUnshare>
    <CascadeRollupView>NoCascade</CascadeRollupView>
    <IsValidForAdvancedFind>1</IsValidForAdvancedFind>
    <ReferencingAttributeName>New_ServiceAgentId</ReferencingAttributeName>
    <RelationshipDescription>
      <Descriptions>
        <Description description="Service Agent (Account)" languagecode="1033" />
      </Descriptions>
    </RelationshipDescription>
    <EntityRelationshipRoles>
      <EntityRelationshipRole>
        <NavPaneDisplayOption>DoNotDisplay</NavPaneDisplayOption>
        <NavPaneArea>Details</NavPaneArea>
        <NavPaneOrder>10000</NavPaneOrder>
        <NavigationPropertyName>new_serviceagentid</NavigationPropertyName>
        <CustomLabels>
          <CustomLabel description="" languagecode="1033" />
        </CustomLabels>
        <RelationshipRoleType>1</RelationshipRoleType>
      </EntityRelationshipRole>
      <EntityRelationshipRole>
        <NavigationPropertyName>new_account_new_certificateofcompliance1</NavigationPropertyName>
        <RelationshipRoleType>0</RelationshipRoleType>
      </EntityRelationshipRole>
    </EntityRelationshipRoles>
  </EntityRelationship>
  <EntityRelationship Name="new_account_new_opportunityhistory">
    <EntityRelationshipType>OneToMany</EntityRelationshipType>
    <IsCustomizable>1</IsCustomizable>
    <IntroducedVersion>1.0</IntroducedVersion>
    <IsHierarchical>0</IsHierarchical>
    <ReferencingEntityName>New_opportunityhistory</ReferencingEntityName>
    <ReferencedEntityName>Account</ReferencedEntityName>
    <CascadeAssign>NoCascade</CascadeAssign>
    <CascadeDelete>Restrict</CascadeDelete>
    <CascadeReparent>NoCascade</CascadeReparent>
    <CascadeShare>NoCascade</CascadeShare>
    <CascadeUnshare>NoCascade</CascadeUnshare>
    <CascadeRollupView>NoCascade</CascadeRollupView>
    <IsValidForAdvancedFind>1</IsValidForAdvancedFind>
    <ReferencingAttributeName>New_PotentialCustomerId</ReferencingAttributeName>
    <RelationshipDescription>
      <Descriptions>
        <Description description="Unique identifier for Account associated with Opportunity History." languagecode="1033" />
      </Descriptions>
    </RelationshipDescription>
    <EntityRelationshipRoles>
      <EntityRelationshipRole>
        <NavPaneDisplayOption>DoNotDisplay</NavPaneDisplayOption>
        <NavPaneArea>Details</NavPaneArea>
        <NavigationPropertyName>new_potentialcustomerid</NavigationPropertyName>
        <CustomLabels>
          <CustomLabel description="" languagecode="1033" />
        </CustomLabels>
        <RelationshipRoleType>1</RelationshipRoleType>
      </EntityRelationshipRole>
      <EntityRelationshipRole>
        <NavigationPropertyName>new_account_new_opportunityhistory</NavigationPropertyName>
        <RelationshipRoleType>0</RelationshipRoleType>
      </EntityRelationshipRole>
    </EntityRelationshipRoles>
  </EntityRelationship>
  <EntityRelationship Name="new_account_new_siteproductgroup">
    <EntityRelationshipType>OneToMany</EntityRelationshipType>
    <IsCustomizable>1</IsCustomizable>
    <IntroducedVersion>1.0</IntroducedVersion>
    <IsHierarchical>0</IsHierarchical>
    <ReferencingEntityName>New_siteproductgroup</ReferencingEntityName>
    <ReferencedEntityName>Account</ReferencedEntityName>
    <CascadeAssign>Cascade</CascadeAssign>
    <CascadeDelete>Cascade</CascadeDelete>
    <CascadeReparent>Cascade</CascadeReparent>
    <CascadeShare>Cascade</CascadeShare>
    <CascadeUnshare>Cascade</CascadeUnshare>
    <CascadeRollupView>NoCascade</CascadeRollupView>
    <IsValidForAdvancedFind>1</IsValidForAdvancedFind>
    <ReferencingAttributeName>New_account</ReferencingAttributeName>
    <RelationshipDescription>
      <Descriptions>
        <Description description="Unique identifier for Account associated with Site Product Group." languagecode="1033" />
      </Descriptions>
    </RelationshipDescription>
    <EntityRelationshipRoles>
      <EntityRelationshipRole>
        <NavPaneDisplayOption>UseCollectionName</NavPaneDisplayOption>
        <NavPaneArea>Details</NavPaneArea>
        <NavPaneOrder>10000</NavPaneOrder>
        <NavigationPropertyName>new_account</NavigationPropertyName>
        <CustomLabels>
          <CustomLabel description="" languagecode="1033" />
        </CustomLabels>
        <RelationshipRoleType>1</RelationshipRoleType>
      </EntityRelationshipRole>
      <EntityRelationshipRole>
        <NavigationPropertyName>new_account_new_siteproductgroup</NavigationPropertyName>
        <RelationshipRoleType>0</RelationshipRoleType>
      </EntityRelationshipRole>
    </EntityRelationshipRoles>
  </EntityRelationship>
  <EntityRelationship Name="new_account_new_vessels_ParentAccount">
    <EntityRelationshipType>OneToMany</EntityRelationshipType>
    <IsCustomizable>1</IsCustomizable>
    <IntroducedVersion>1.17.3.30</IntroducedVersion>
    <IsHierarchical>0</IsHierarchical>
    <ReferencingEntityName>new_vessels</ReferencingEntityName>
    <ReferencedEntityName>Account</ReferencedEntityName>
    <CascadeAssign>NoCascade</CascadeAssign>
    <CascadeDelete>RemoveLink</CascadeDelete>
    <CascadeReparent>NoCascade</CascadeReparent>
    <CascadeShare>NoCascade</CascadeShare>
    <CascadeUnshare>NoCascade</CascadeUnshare>
    <CascadeRollupView>NoCascade</CascadeRollupView>
    <IsValidForAdvancedFind>1</IsValidForAdvancedFind>
    <ReferencingAttributeName>new_ParentAccount</ReferencingAttributeName>
    <RelationshipDescription>
      <Descriptions>
        <Description description="" languagecode="1033" />
      </Descriptions>
    </RelationshipDescription>
    <EntityRelationshipRoles>
      <EntityRelationshipRole>
        <NavPaneDisplayOption>UseCollectionName</NavPaneDisplayOption>
        <NavPaneArea>Details</NavPaneArea>
        <NavPaneOrder>10000</NavPaneOrder>
        <NavigationPropertyName>new_ParentAccount</NavigationPropertyName>
        <CustomLabels>
          <CustomLabel description="" languagecode="1033" />
        </CustomLabels>
        <RelationshipRoleType>1</RelationshipRoleType>
      </EntityRelationshipRole>
      <EntityRelationshipRole>
        <NavigationPropertyName>new_account_new_vessels_ParentAccount</NavigationPropertyName>
        <RelationshipRoleType>0</RelationshipRoleType>
      </EntityRelationshipRole>
    </EntityRelationshipRoles>
  </EntityRelationship>
  <EntityRelationship Name="opportunity_customer_accounts">
    <EntityRelationshipType>OneToMany</EntityRelationshipType>
    <IntroducedVersion>5.0.0.0</IntroducedVersion>
    <IsHierarchical>0</IsHierarchical>
    <ReferencingEntityName>Opportunity</ReferencingEntityName>
    <ReferencedEntityName>Account</ReferencedEntityName>
    <CascadeAssign>NoCascade</CascadeAssign>
    <CascadeDelete>Cascade</CascadeDelete>
    <CascadeReparent>NoCascade</CascadeReparent>
    <CascadeShare>NoCascade</CascadeShare>
    <CascadeUnshare>NoCascade</CascadeUnshare>
    <ReferencingAttributeName>CustomerId</ReferencingAttributeName>
    <RelationshipDescription>
      <Descriptions>
        <Description description="Select the customer account or contact to provide a quick link to additional customer details, such as address, phone number, activities, and orders." languagecode="1033" />
      </Descriptions>
    </RelationshipDescription>
    <EntityRelationshipRoles>
      <EntityRelationshipRole>
        <NavPaneDisplayOption>DoNotDisplay</NavPaneDisplayOption>
        <NavPaneArea>Sales</NavPaneArea>
        <NavPaneOrder>10</NavPaneOrder>
        <NavigationPropertyName>customerid_account</NavigationPropertyName>
        <RelationshipRoleType>1</RelationshipRoleType>
      </EntityRelationshipRole>
      <EntityRelationshipRole>
        <RelationshipRoleType>0</RelationshipRoleType>
      </EntityRelationshipRole>
    </EntityRelationshipRoles>
  </EntityRelationship>
  <EntityRelationship Name="opportunity_parent_account">
    <EntityRelationshipType>OneToMany</EntityRelationshipType>
    <IntroducedVersion>5.0.0.0</IntroducedVersion>
    <IsHierarchical>0</IsHierarchical>
    <ReferencingEntityName>Opportunity</ReferencingEntityName>
    <ReferencedEntityName>Account</ReferencedEntityName>
    <CascadeAssign>NoCascade</CascadeAssign>
    <CascadeDelete>RemoveLink</CascadeDelete>
    <CascadeReparent>NoCascade</CascadeReparent>
    <CascadeShare>NoCascade</CascadeShare>
    <CascadeUnshare>NoCascade</CascadeUnshare>
    <ReferencingAttributeName>ParentAccountId</ReferencingAttributeName>
    <RelationshipDescription>
      <Descriptions>
        <Description description="Choose an account to connect this opportunity to, so that the relationship is visible in reports and analytics, and to provide a quick link to additional details, such as financial information and activities." languagecode="1033" />
      </Descriptions>
    </RelationshipDescription>
    <EntityRelationshipRoles>
      <EntityRelationshipRole>
        <NavPaneDisplayOption>UseCollectionName</NavPaneDisplayOption>
        <NavPaneArea>Sales</NavPaneArea>
        <NavPaneOrder>10000</NavPaneOrder>
        <NavigationPropertyName>parentaccountid</NavigationPropertyName>
        <RelationshipRoleType>1</RelationshipRoleType>
      </EntityRelationshipRole>
      <EntityRelationshipRole>
        <RelationshipRoleType>0</RelationshipRoleType>
      </EntityRelationshipRole>
    </EntityRelationshipRoles>
  </EntityRelationship>
  <EntityRelationship Name="order_customer_accounts">
    <EntityRelationshipType>OneToMany</EntityRelationshipType>
    <IntroducedVersion>5.0.0.0</IntroducedVersion>
    <IsHierarchical>0</IsHierarchical>
    <ReferencingEntityName>SalesOrder</ReferencingEntityName>
    <ReferencedEntityName>Account</ReferencedEntityName>
    <CascadeAssign>Cascade</CascadeAssign>
    <CascadeDelete>Restrict</CascadeDelete>
    <CascadeReparent>Cascade</CascadeReparent>
    <CascadeShare>Cascade</CascadeShare>
    <CascadeUnshare>Cascade</CascadeUnshare>
    <ReferencingAttributeName>CustomerId</ReferencingAttributeName>
    <RelationshipDescription>
      <Descriptions>
        <Description description="order_customer_contacts" languagecode="1033" />
      </Descriptions>
    </RelationshipDescription>
    <EntityRelationshipRoles>
      <EntityRelationshipRole>
        <NavPaneDisplayOption>UseCollectionName</NavPaneDisplayOption>
        <NavPaneArea>Sales</NavPaneArea>
        <NavPaneOrder>30</NavPaneOrder>
        <NavigationPropertyName>customerid_account</NavigationPropertyName>
        <RelationshipRoleType>1</RelationshipRoleType>
      </EntityRelationshipRole>
      <EntityRelationshipRole>
        <RelationshipRoleType>0</RelationshipRoleType>
      </EntityRelationshipRole>
    </EntityRelationshipRoles>
  </EntityRelationship>
  <EntityRelationship Name="quote_customer_accounts">
    <EntityRelationshipType>OneToMany</EntityRelationshipType>
    <IntroducedVersion>5.0.0.0</IntroducedVersion>
    <IsHierarchical>0</IsHierarchical>
    <ReferencingEntityName>Quote</ReferencingEntityName>
    <ReferencedEntityName>Account</ReferencedEntityName>
    <CascadeAssign>Cascade</CascadeAssign>
    <CascadeDelete>Cascade</CascadeDelete>
    <CascadeReparent>Cascade</CascadeReparent>
    <CascadeShare>Cascade</CascadeShare>
    <CascadeUnshare>Cascade</CascadeUnshare>
    <ReferencingAttributeName>CustomerId</ReferencingAttributeName>
    <RelationshipDescription>
      <Descriptions>
        <Description description="quote_customer_contacts" languagecode="1033" />
      </Descriptions>
    </RelationshipDescription>
    <EntityRelationshipRoles>
      <EntityRelationshipRole>
        <NavPaneDisplayOption>UseCollectionName</NavPaneDisplayOption>
        <NavPaneArea>Sales</NavPaneArea>
        <NavPaneOrder>20</NavPaneOrder>
        <NavigationPropertyName>customerid_account</NavigationPropertyName>
        <RelationshipRoleType>1</RelationshipRoleType>
      </EntityRelationshipRole>
      <EntityRelationshipRole>
        <RelationshipRoleType>0</RelationshipRoleType>
      </EntityRelationshipRole>
    </EntityRelationshipRoles>
  </EntityRelationship>
  <EntityRelationship Name="tra_account_incident_ServiceSupplier">
    <EntityRelationshipType>OneToMany</EntityRelationshipType>
    <IsCustomizable>1</IsCustomizable>
    <IntroducedVersion>0.1.1.1</IntroducedVersion>
    <IsHierarchical>0</IsHierarchical>
    <ReferencingEntityName>Incident</ReferencingEntityName>
    <ReferencedEntityName>Account</ReferencedEntityName>
    <CascadeAssign>NoCascade</CascadeAssign>
    <CascadeDelete>Restrict</CascadeDelete>
    <CascadeReparent>NoCascade</CascadeReparent>
    <CascadeShare>NoCascade</CascadeShare>
    <CascadeUnshare>NoCascade</CascadeUnshare>
    <CascadeRollupView>NoCascade</CascadeRollupView>
    <IsValidForAdvancedFind>1</IsValidForAdvancedFind>
    <ReferencingAttributeName>tra_ServiceSupplier</ReferencingAttributeName>
    <RelationshipDescription>
      <Descriptions>
        <Description description="" languagecode="1033" />
      </Descriptions>
    </RelationshipDescription>
    <EntityRelationshipRoles>
      <EntityRelationshipRole>
        <NavPaneDisplayOption>UseCollectionName</NavPaneDisplayOption>
        <NavPaneArea>Details</NavPaneArea>
        <NavPaneOrder>10000</NavPaneOrder>
        <NavigationPropertyName>tra_ServiceSupplier</NavigationPropertyName>
        <CustomLabels>
          <CustomLabel description="" languagecode="1033" />
        </CustomLabels>
        <RelationshipRoleType>1</RelationshipRoleType>
      </EntityRelationshipRole>
      <EntityRelationshipRole>
        <NavigationPropertyName>tra_account_incident_ServiceSupplier</NavigationPropertyName>
        <RelationshipRoleType>0</RelationshipRoleType>
      </EntityRelationshipRole>
    </EntityRelationshipRoles>
  </EntityRelationship>
  <EntityRelationship Name="tra_account_new_vessels_ShipManager">
    <EntityRelationshipType>OneToMany</EntityRelationshipType>
    <IsCustomizable>1</IsCustomizable>
    <IntroducedVersion>0.1</IntroducedVersion>
    <IsHierarchical>0</IsHierarchical>
    <ReferencingEntityName>new_vessels</ReferencingEntityName>
    <ReferencedEntityName>Account</ReferencedEntityName>
    <CascadeAssign>NoCascade</CascadeAssign>
    <CascadeDelete>RemoveLink</CascadeDelete>
    <CascadeReparent>NoCascade</CascadeReparent>
    <CascadeShare>NoCascade</CascadeShare>
    <CascadeUnshare>NoCascade</CascadeUnshare>
    <CascadeRollupView>NoCascade</CascadeRollupView>
    <IsValidForAdvancedFind>1</IsValidForAdvancedFind>
    <ReferencingAttributeName>tra_ShipManager</ReferencingAttributeName>
    <RelationshipDescription>
      <Descriptions>
        <Description description="" languagecode="1033" />
      </Descriptions>
    </RelationshipDescription>
    <EntityRelationshipRoles>
      <EntityRelationshipRole>
        <NavPaneDisplayOption>UseCollectionName</NavPaneDisplayOption>
        <NavPaneArea>Details</NavPaneArea>
        <NavPaneOrder>10000</NavPaneOrder>
        <NavigationPropertyName>tra_ShipManager</NavigationPropertyName>
        <CustomLabels>
          <CustomLabel description="" languagecode="1033" />
        </CustomLabels>
        <RelationshipRoleType>1</RelationshipRoleType>
      </EntityRelationshipRole>
      <EntityRelationshipRole>
        <NavigationPropertyName>tra_account_new_vessels_ShipManager</NavigationPropertyName>
        <RelationshipRoleType>0</RelationshipRoleType>
      </EntityRelationshipRole>
    </EntityRelationshipRoles>
  </EntityRelationship>
  <EntityRelationship Name="tra_account_of_regarding_appointment">
    <EntityRelationshipType>OneToMany</EntityRelationshipType>
    <IsCustomizable>1</IsCustomizable>
    <IntroducedVersion>0.1</IntroducedVersion>
    <IsHierarchical>0</IsHierarchical>
    <ReferencingEntityName>Appointment</ReferencingEntityName>
    <ReferencedEntityName>Account</ReferencedEntityName>
    <CascadeAssign>NoCascade</CascadeAssign>
    <CascadeDelete>RemoveLink</CascadeDelete>
    <CascadeReparent>NoCascade</CascadeReparent>
    <CascadeShare>NoCascade</CascadeShare>
    <CascadeUnshare>NoCascade</CascadeUnshare>
    <CascadeRollupView>NoCascade</CascadeRollupView>
    <IsValidForAdvancedFind>1</IsValidForAdvancedFind>
    <ReferencingAttributeName>tra_AccountOfRegardingEntityId</ReferencingAttributeName>
    <RelationshipDescription>
      <Descriptions>
        <Description description="Unique identifier for Account associated with Appointment." languagecode="1033" />
      </Descriptions>
    </RelationshipDescription>
    <EntityRelationshipRoles>
      <EntityRelationshipRole>
        <NavPaneDisplayOption>UseCollectionName</NavPaneDisplayOption>
        <NavPaneArea>Details</NavPaneArea>
        <NavPaneOrder>10000</NavPaneOrder>
        <NavigationPropertyName>tra_AccountOfRegardingEntityId_Appointment</NavigationPropertyName>
        <CustomLabels>
          <CustomLabel description="" languagecode="1033" />
        </CustomLabels>
        <RelationshipRoleType>1</RelationshipRoleType>
      </EntityRelationshipRole>
      <EntityRelationshipRole>
        <NavigationPropertyName>tra_account_of_regarding_appointment</NavigationPropertyName>
        <RelationshipRoleType>0</RelationshipRoleType>
      </EntityRelationshipRole>
    </EntityRelationshipRoles>
  </EntityRelationship>
  <EntityRelationship Name="tra_account_phonecall">
    <EntityRelationshipType>OneToMany</EntityRelationshipType>
    <IsCustomizable>1</IsCustomizable>
    <IntroducedVersion>1.0</IntroducedVersion>
    <IsHierarchical>0</IsHierarchical>
    <ReferencingEntityName>PhoneCall</ReferencingEntityName>
    <ReferencedEntityName>Account</ReferencedEntityName>
    <CascadeAssign>NoCascade</CascadeAssign>
    <CascadeDelete>RemoveLink</CascadeDelete>
    <CascadeReparent>NoCascade</CascadeReparent>
    <CascadeShare>NoCascade</CascadeShare>
    <CascadeUnshare>NoCascade</CascadeUnshare>
    <CascadeRollupView>NoCascade</CascadeRollupView>
    <IsValidForAdvancedFind>1</IsValidForAdvancedFind>
    <ReferencingAttributeName>tra_accountofregardingentityid</ReferencingAttributeName>
    <RelationshipDescription>
      <Descriptions>
        <Description description="Unique identifier for Account associated with Phone Call." languagecode="1033" />
      </Descriptions>
    </RelationshipDescription>
    <EntityRelationshipRoles>
      <EntityRelationshipRole>
        <NavPaneDisplayOption>UseCollectionName</NavPaneDisplayOption>
        <NavPaneArea>Details</NavPaneArea>
        <NavPaneOrder>10000</NavPaneOrder>
        <NavigationPropertyName>tra_accountofregardingentityid_PhoneCall</NavigationPropertyName>
        <CustomLabels>
          <CustomLabel description="" languagecode="1033" />
        </CustomLabels>
        <RelationshipRoleType>1</RelationshipRoleType>
      </EntityRelationshipRole>
      <EntityRelationshipRole>
        <NavigationPropertyName>tra_account_phonecall</NavigationPropertyName>
        <RelationshipRoleType>0</RelationshipRoleType>
      </EntityRelationshipRole>
    </EntityRelationshipRoles>
  </EntityRelationship>
  <EntityRelationship Name="tra_account_tra_questionnaire">
    <EntityRelationshipType>OneToMany</EntityRelationshipType>
    <IsCustomizable>1</IsCustomizable>
    <IntroducedVersion>0.1</IntroducedVersion>
    <IsHierarchical>0</IsHierarchical>
    <ReferencingEntityName>tra_questionnaire</ReferencingEntityName>
    <ReferencedEntityName>Account</ReferencedEntityName>
    <CascadeAssign>NoCascade</CascadeAssign>
    <CascadeDelete>RemoveLink</CascadeDelete>
    <CascadeReparent>NoCascade</CascadeReparent>
    <CascadeShare>NoCascade</CascadeShare>
    <CascadeUnshare>NoCascade</CascadeUnshare>
    <CascadeRollupView>NoCascade</CascadeRollupView>
    <IsValidForAdvancedFind>1</IsValidForAdvancedFind>
    <ReferencingAttributeName>tra_QustionnairesofAccountId</ReferencingAttributeName>
    <RelationshipDescription>
      <Descriptions>
        <Description description="Unique identifier for Account associated with Bundles Survey." languagecode="1033" />
      </Descriptions>
    </RelationshipDescription>
    <EntityRelationshipRoles>
      <EntityRelationshipRole>
        <NavPaneDisplayOption>UseCollectionName</NavPaneDisplayOption>
        <NavPaneArea>Details</NavPaneArea>
        <NavPaneOrder>10000</NavPaneOrder>
        <NavigationPropertyName>tra_QustionnairesofAccountId</NavigationPropertyName>
        <CustomLabels>
          <CustomLabel description="" languagecode="1033" />
        </CustomLabels>
        <RelationshipRoleType>1</RelationshipRoleType>
      </EntityRelationshipRole>
      <EntityRelationshipRole>
        <NavigationPropertyName>tra_account_tra_questionnaire</NavigationPropertyName>
        <RelationshipRoleType>0</RelationshipRoleType>
      </EntityRelationshipRole>
    </EntityRelationshipRoles>
  </EntityRelationship>
  <EntityRelationship Name="tra_account_tra_trainingcertificate_CompanyAccount">
    <EntityRelationshipType>OneToMany</EntityRelationshipType>
    <IsCustomizable>1</IsCustomizable>
    <IntroducedVersion>18.12.12.0</IntroducedVersion>
    <IsHierarchical>0</IsHierarchical>
    <ReferencingEntityName>tra_trainingcertificate</ReferencingEntityName>
    <ReferencedEntityName>Account</ReferencedEntityName>
    <CascadeAssign>NoCascade</CascadeAssign>
    <CascadeDelete>RemoveLink</CascadeDelete>
    <CascadeReparent>NoCascade</CascadeReparent>
    <CascadeShare>NoCascade</CascadeShare>
    <CascadeUnshare>NoCascade</CascadeUnshare>
    <CascadeRollupView>NoCascade</CascadeRollupView>
    <IsValidForAdvancedFind>1</IsValidForAdvancedFind>
    <ReferencingAttributeName>tra_Account</ReferencingAttributeName>
    <RelationshipDescription>
      <Descriptions>
        <Description description="" languagecode="1033" />
      </Descriptions>
    </RelationshipDescription>
    <EntityRelationshipRoles>
      <EntityRelationshipRole>
        <NavPaneDisplayOption>UseCollectionName</NavPaneDisplayOption>
        <NavPaneArea>Details</NavPaneArea>
        <NavPaneOrder>10000</NavPaneOrder>
        <NavigationPropertyName>tra_Account</NavigationPropertyName>
        <CustomLabels>
          <CustomLabel description="" languagecode="1033" />
        </CustomLabels>
        <RelationshipRoleType>1</RelationshipRoleType>
      </EntityRelationshipRole>
      <EntityRelationshipRole>
        <NavigationPropertyName>tra_account_tra_trainingcertificate_CompanyAccount</NavigationPropertyName>
        <RelationshipRoleType>0</RelationshipRoleType>
      </EntityRelationshipRole>
    </EntityRelationshipRoles>
  </EntityRelationship>
  <EntityRelationship Name="tra_account_tra_vesselentitlement">
    <EntityRelationshipType>OneToMany</EntityRelationshipType>
    <IsCustomizable>1</IsCustomizable>
    <IntroducedVersion>1.0</IntroducedVersion>
    <IsHierarchical>0</IsHierarchical>
    <ReferencingEntityName>tra_vesselentitlement</ReferencingEntityName>
    <ReferencedEntityName>Account</ReferencedEntityName>
    <CascadeAssign>NoCascade</CascadeAssign>
    <CascadeDelete>RemoveLink</CascadeDelete>
    <CascadeReparent>NoCascade</CascadeReparent>
    <CascadeShare>NoCascade</CascadeShare>
    <CascadeUnshare>NoCascade</CascadeUnshare>
    <CascadeRollupView>NoCascade</CascadeRollupView>
    <IsValidForAdvancedFind>1</IsValidForAdvancedFind>
    <ReferencingAttributeName>tra_AccountId</ReferencingAttributeName>
    <RelationshipDescription>
      <Descriptions>
        <Description description="Unique identifier for Account associated with Vessel Entitlement." languagecode="1033" />
      </Descriptions>
    </RelationshipDescription>
    <EntityRelationshipRoles>
      <EntityRelationshipRole>
        <NavPaneDisplayOption>UseCollectionName</NavPaneDisplayOption>
        <NavPaneArea>Details</NavPaneArea>
        <NavPaneOrder>10000</NavPaneOrder>
        <NavigationPropertyName>tra_AccountId</NavigationPropertyName>
        <CustomLabels>
          <CustomLabel description="" languagecode="1033" />
        </CustomLabels>
        <RelationshipRoleType>1</RelationshipRoleType>
      </EntityRelationshipRole>
      <EntityRelationshipRole>
        <NavigationPropertyName>tra_account_tra_vesselentitlement</NavigationPropertyName>
        <RelationshipRoleType>0</RelationshipRoleType>
      </EntityRelationshipRole>
    </EntityRelationshipRoles>
  </EntityRelationship>
  <EntityRelationship Name="wdt_account_new_accountproduct_thirdpartyacc">
    <EntityRelationshipType>OneToMany</EntityRelationshipType>
    <IsCustomizable>1</IsCustomizable>
    <IntroducedVersion>0.44.2.2</IntroducedVersion>
    <IsHierarchical>0</IsHierarchical>
    <ReferencingEntityName>New_AccountProduct</ReferencingEntityName>
    <ReferencedEntityName>Account</ReferencedEntityName>
    <CascadeAssign>NoCascade</CascadeAssign>
    <CascadeDelete>RemoveLink</CascadeDelete>
    <CascadeReparent>NoCascade</CascadeReparent>
    <CascadeShare>NoCascade</CascadeShare>
    <CascadeUnshare>NoCascade</CascadeUnshare>
    <CascadeRollupView>NoCascade</CascadeRollupView>
    <IsValidForAdvancedFind>1</IsValidForAdvancedFind>
    <ReferencingAttributeName>wdt_ThirdPartyAccountId</ReferencingAttributeName>
    <RelationshipDescription>
      <Descriptions>
        <Description description="Unique identifier for Account associated with Account Product." languagecode="1033" />
      </Descriptions>
    </RelationshipDescription>
    <EntityRelationshipRoles>
      <EntityRelationshipRole>
        <NavPaneDisplayOption>UseLabel</NavPaneDisplayOption>
        <NavPaneArea>Sales</NavPaneArea>
        <NavPaneOrder>10000</NavPaneOrder>
        <NavigationPropertyName>wdt_ThirdPartyAccountId</NavigationPropertyName>
        <CustomLabels>
          <CustomLabel description="Account Products (as Third Party Account)" languagecode="1033" />
        </CustomLabels>
        <RelationshipRoleType>1</RelationshipRoleType>
      </EntityRelationshipRole>
      <EntityRelationshipRole>
        <NavigationPropertyName>wdt_account_new_accountproduct_thirdpartyacc</NavigationPropertyName>
        <RelationshipRoleType>0</RelationshipRoleType>
      </EntityRelationshipRole>
    </EntityRelationshipRoles>
  </EntityRelationship>
  <EntityRelationship Name="wdt_account_new_vessels_distributor">
    <EntityRelationshipType>OneToMany</EntityRelationshipType>
    <IsCustomizable>1</IsCustomizable>
    <IntroducedVersion>0.44.5.8</IntroducedVersion>
    <IsHierarchical>0</IsHierarchical>
    <ReferencingEntityName>new_vessels</ReferencingEntityName>
    <ReferencedEntityName>Account</ReferencedEntityName>
    <CascadeAssign>NoCascade</CascadeAssign>
    <CascadeDelete>RemoveLink</CascadeDelete>
    <CascadeReparent>NoCascade</CascadeReparent>
    <CascadeShare>NoCascade</CascadeShare>
    <CascadeUnshare>NoCascade</CascadeUnshare>
    <CascadeRollupView>NoCascade</CascadeRollupView>
    <IsValidForAdvancedFind>1</IsValidForAdvancedFind>
    <ReferencingAttributeName>wdt_DistributorId</ReferencingAttributeName>
    <RelationshipDescription>
      <Descriptions>
        <Description description="Unique identifier for Account associated with Vessel." languagecode="1033" />
      </Descriptions>
    </RelationshipDescription>
    <EntityRelationshipRoles>
      <EntityRelationshipRole>
        <NavPaneDisplayOption>UseLabel</NavPaneDisplayOption>
        <NavPaneArea>Service</NavPaneArea>
        <NavPaneOrder>10000</NavPaneOrder>
        <NavigationPropertyName>wdt_DistributorId</NavigationPropertyName>
        <CustomLabels>
          <CustomLabel description="" languagecode="1033" />
        </CustomLabels>
        <RelationshipRoleType>1</RelationshipRoleType>
      </EntityRelationshipRole>
      <EntityRelationshipRole>
        <NavigationPropertyName>wdt_account_new_vessels_distributor</NavigationPropertyName>
        <RelationshipRoleType>0</RelationshipRoleType>
      </EntityRelationshipRole>
    </EntityRelationshipRoles>
  </EntityRelationship>
</EntityRelationships>